AUTHORS.rst
HISTORY.rst
LICENSE.txt
MANIFEST.in
README.rst
jsonte.py
requirements.txt
setup.py
test_jsonte.py
jsonte.egg-info/PKG-INFO
jsonte.egg-info/SOURCES.txt
jsonte.egg-info/dependency_links.txt
jsonte.egg-info/not-zip-safe
jsonte.egg-info/requires.txt
jsonte.egg-info/top_level.txt