Metadata-Version: 1.1
Name: jsonte
Version: 0.8.5
Summary: Json Type Extensions.
Home-page: https://github.com/rasjidw/python-jsonte
Author: Rasjid Wilcox
Author-email: rasjidw@openminddev.net
License: BSD
Keywords: jsonte
Platform: UNKNOWN
Classifier: Development Status :: 4 - Beta
Classifier: Intended Audience :: Developers
Classifier: License :: OSI Approved :: BSD License
Classifier: Natural Language :: English
Classifier: Programming Language :: Python :: 2.6
Classifier: Programming Language :: Python :: 2.7
Classifier: Programming Language :: Python :: 3.3
Classifier: Programming Language :: Python :: 3.4
